benchmark/__init__.py
entityset/__init__.py
entityset/util.py
entityset-0.0.1.dist-info/LICENSE
entityset-0.0.1.dist-info/METADATA
entityset-0.0.1.dist-info/WHEEL
entityset-0.0.1.dist-info/top_level.txt
entityset-0.0.1.dist-info/RECORD
