Metadata-Version: 2.1
Name: entityset
Version: 0.0.1
Summary: Entityset python library
Home-page: UNKNOWN
Author: SpaceGPT Team
Author-email: silveryfu@gmail.com
License: Apache License, Version 2.0
Platform: UNKNOWN
Requires-Python: >=3.8
Requires-Dist: openai
Requires-Dist: pyyaml
Requires-Dist: numpy
Requires-Dist: bs4
Requires-Dist: pandas
